nicos
nicos_batan
nicos_demo
nicos_ess
nicos_inl
nicos_isis
nicos_jcns
nicos_lahn
nicos_mgml
nicos_mlz
nicos_pnpi
nicos_sinq
nicos_tum
nicos_tuw
nicos_virt_mlz
