Metadata-Version: 2.1
Name: nicos
Version: 3.12.2
Summary: The Networked Instrument Control System
Home-page: https://www.nicos-controls.org
Author: Georg Brandl
Author-email: g.brandl@fz-juelich.de
Maintainer: Jens Krüger
Maintainer-email: jens.krueger@frm2.tum.de
License: GPL
Project-URL: Documentation, https://forge.frm2.tum.de/nicos/doc/nicos-master/documentation/
Project-URL: Source, https://forge.frm2.tum.de/cgit/cgit.cgi/frm2/nicos/nicos-core.git/
Project-URL: Tracker, https://forge.frm2.tum.de/redmine/projects/nicos/issues
Classifier: Development Status :: 5 - Production/Stable
Classifier: Intended Audience :: Developers
Classifier: Intended Audience :: Science/Research
Classifier: Natural Language :: English
Classifier: Operating System :: OS Independent
Classifier: Programming Language :: Python
Classifier: Programming Language :: Python :: 3
Classifier: Programming Language :: Python :: 3.9
Classifier: Programming Language :: Python :: 3.10
Classifier: Programming Language :: Python :: 3.11
Classifier: Programming Language :: Python :: 3.12
Classifier: Programming Language :: Python :: 3.13
Classifier: Topic :: Scientific/Engineering
Classifier: Topic :: Scientific/Engineering :: Human Machine Interfaces
Classifier: Topic :: Scientific/Engineering :: Physics
Classifier: Topic :: Scientific/Engineering :: Visualization
License-File: LICENSE
License-File: AUTHORS
